mkn/__init__.py
mkn/sample.py
mkn-0.0.5.dist-info/LICENSE
mkn-0.0.5.dist-info/METADATA
mkn-0.0.5.dist-info/WHEEL
mkn-0.0.5.dist-info/top_level.txt
mkn-0.0.5.dist-info/RECORD
