Metadata-Version: 2.1
Name: mkn
Version: 0.0.5
Summary: A minimum PyPI project
Home-page: https://github.com/mojikimino/mkn
Author: Moji Kimino
Author-email: UNKNOWN
License: UNKNOWN
Download-URL: https://github.com/mojikimino/mkn/archive/0.0.5.tar.gz
Platform: UNKNOWN
Requires-Dist: pytest
